{
  "posts": [
    {
      "id": 1,
      "title": "json-server",
      "author": "typicode"
    }
  ],
  "comments": [
    {
      "id": 1,
      "body": "some comment",
      "postId": 1
    }
  ],
  "profile": {
    "name": "typicode"
  },
  "items": [
    {
      "itemTitle": "computer",
      "itemDesc": "shh",
      "category": "Electronic",
      "price": 5000,
      "date": "2023-04-20T18:30:00.000Z",
      "id": 3
    },
    {
      "itemTitle": "Phone",
      "itemDesc": "Iphone X",
      "category": "Electronic",
      "price": 25000,
      "date": "2023-04-21T18:30:00.000Z",
      "country": "",
      "id": 4
    },
    {
      "itemTitle": "apple",
      "itemDesc": "100g",
      "category": "Food",
      "price": 100,
      "date": "2023-04-21T18:30:00.000Z",
      "country": "",
      "id": 5
    },
    {
      "itemTitle": "orange",
      "itemDesc": "500g",
      "category": "Electronic",
      "price": 22,
      "date": "2023-04-27T18:30:00.000Z",
      "country": "United States",
      "id": 10
    },
    {
      "itemTitle": "dfd",
      "itemDesc": "dfd",
      "category": "Food",
      "price": 32,
      "date": "2023-04-26T18:30:00.000Z",
      "country": "",
      "id": 11
    }
  ]
}